decorators/__init__.py
decorators/timing.py
decorators_dunningrb-0.1.0.dist-info/METADATA
decorators_dunningrb-0.1.0.dist-info/WHEEL
decorators_dunningrb-0.1.0.dist-info/top_level.txt
decorators_dunningrb-0.1.0.dist-info/RECORD
